xkcd_comicdb/__init__.py
xkcd_comicdb/xkcd.sqlite3
xkcd_comicdb-2022.8.31.dist-info/METADATA
xkcd_comicdb-2022.8.31.dist-info/WHEEL
xkcd_comicdb-2022.8.31.dist-info/top_level.txt
xkcd_comicdb-2022.8.31.dist-info/RECORD
